{"py/object": "rasa.core.featurizers.tracker_featurizers.MaxHistoryTrackerFeaturizer", "state_featurizer": {"py/object": "rasa.core.featurizers.single_state_featurizer.SingleStateFeaturizer", "_default_feature_states": {"intent": {"account_balance": 0, "affirm": 1, "back": 2, "bot_challenge": 3, "deny": 4, "give_card_id": 5, "goodbye": 6, "greet": 7, "how_activate_my_card": 8, "how_apple_pay_or_google_pay": 9, "how_automatic_top_up": 10, "how_card_about_to_expire": 11, "how_card_arrival": 12, "how_card_linking": 13, "how_card_not_working": 14, "how_card_payment_fee_charged": 15, "how_card_swallowed": 16, "how_change_pin": 17, "how_compromised_card": 18, "how_contactless_not_working": 19, "how_country_support": 20, "how_declined_transfer": 21, "how_direct_debit_payment_not_recognised": 22, "how_edit_personal_details": 23, "how_exchange_rate": 24, "how_exchange_via_app": 25, "how_get_disposable_virtual_card": 26, "how_get_physical_card": 27, "how_getting_spare_card": 28, "how_getting_virtual_card": 29, "how_lost_or_stolen_card": 30, "how_lost_or_stolen_phone": 31, "how_order_physical_card": 32, "how_passcode_forgotten": 33, "how_pin_blocked": 34, "how_receiving_money": 35, "how_request_refund": 36, "how_supported_cards_and_currencies": 37, "how_terminate_account": 38, "how_top_up_by_cash_or_cheque": 39, "how_topping_up_by_card": 40, "how_transaction_charged_twice": 41, "how_transfer_into_account": 42, "how_verify_my_identity": 43, "how_verify_top_up": 44, "how_wrong_amount_of_cash_received": 45, "mood_great": 46, "mood_unhappy": 47, "nlu_fallback": 48, "out_of_scope": 49, "payment": 50, "restart": 51, "session_start": 52, "user_introduce": 53, "what_age_limit": 54, "what_apple_pay_or_google_pay": 55, "what_atm_support": 56, "what_automatic_top_up": 57, "what_balance_not_updated_after_bank_transfer": 58, "what_card_about_to_expire": 59, "what_card_acceptance": 60, "what_card_arrival": 61, "what_card_delivery_estimate": 62, "what_card_payment_fee_charged": 63, "what_cash_withdrawal_charge": 64, "what_cash_withdrawal_not_recognised": 65, "what_country_support": 66, "what_disposable_card_limits": 67, "what_exchange_charge": 68, "what_exchange_rate": 69, "what_extra_charge_on_statement": 70, "what_fiat_currency_support": 71, "what_get_disposable_virtual_card": 72, "what_pending_cash_withdrawal": 73, "what_pending_transfer": 74, "what_request_refund": 75, "what_supported_cards_and_currencies": 76, "what_top_up_by_bank_transfer_charge": 77, "what_top_up_by_card_charge": 78, "what_top_up_by_cash_or_cheque": 79, "what_top_up_limits": 80, "what_transfer_fee_charged": 81, "what_transfer_timing": 82, "what_verify_identity": 83, "what_verify_top_up": 84, "what_visa_or_mastercard": 85}, "action_name": {"action_listen": 0, "action_restart": 1, "action_session_start": 2, "action_default_fallback": 3, "action_deactivate_loop": 4, "action_revert_fallback_events": 5, "action_default_ask_affirmation": 6, "action_default_ask_rephrase": 7, "action_two_stage_fallback": 8, "action_unlikely_intent": 9, "action_back": 10, "...": 11, "action_extract_slots": 12, "action_show_balance": 13, "action_greet_with_name": 14, "utter_ask_name": 15, "utter_ask_something": 16, "utter_balance": 17, "utter_bill_info": 18, "utter_card_id": 19, "utter_cheer_up": 20, "utter_did_that_help": 21, "utter_goodbye": 22, "utter_greet": 23, "utter_happy": 24, "utter_iamabot": 25}, "entities": {"card_id": 0, "user_name": 1}, "slots": {"user_name_0": 0, "card_id_0": 1}, "active_loop": {}}, "action_texts": [], "entity_tag_specs": []}, "max_history": 5, "remove_duplicates": true}